examples/__init__.py
examples/read_dataset.py
examples/cordeau/__init__.py
examples/cordeau/benchmark_launch.py
examples/cordeau/benchmark_solve.py
examples/cordeau/example_grasp.py
examples/cordeau/example_insertion.py
examples/cordeau/example_milp_three_index.py
examples/cordeau/example_two_opt.py
examples/hashcode/__init__.py
examples/hashcode/example_insertion.py
jinete/__init__.py
jinete/_version.py
jinete/exceptions.py
jinete/solvers.py
jinete/algorithms/__init__.py
jinete/algorithms/abc.py
jinete/algorithms/naive.py
jinete/algorithms/exacts/__init__.py
jinete/algorithms/exacts/milp.py
jinete/algorithms/exacts/models/__init__.py
jinete/algorithms/exacts/models/abc.py
jinete/algorithms/exacts/models/three_index.py
jinete/algorithms/heuristics/__init__.py
jinete/algorithms/heuristics/insertion.py
jinete/algorithms/heuristics/local_search.py
jinete/algorithms/heuristics/insertion/__init__.py
jinete/algorithms/heuristics/insertion/algorithm.py
jinete/algorithms/heuristics/insertion/iterators/__init__.py
jinete/algorithms/heuristics/insertion/iterators/abc.py
jinete/algorithms/heuristics/insertion/iterators/ranking.py
jinete/algorithms/heuristics/insertion/iterators/stateless.py
jinete/algorithms/heuristics/insertion/strategies/__init__.py
jinete/algorithms/heuristics/insertion/strategies/abc.py
jinete/algorithms/heuristics/insertion/strategies/intensive.py
jinete/algorithms/heuristics/insertion/strategies/sampling.py
jinete/algorithms/heuristics/insertion/strategies/tail.py
jinete/algorithms/heuristics/local_search/__init__.py
jinete/algorithms/heuristics/local_search/algorithm.py
jinete/algorithms/heuristics/local_search/strategies/__init__.py
jinete/algorithms/heuristics/local_search/strategies/abc.py
jinete/algorithms/heuristics/local_search/strategies/plannings/__init__.py
jinete/algorithms/heuristics/local_search/strategies/plannings/reallocation.py
jinete/algorithms/heuristics/local_search/strategies/routes/__init__.py
jinete-0.1.0.dist-info/LICENSE
jinete-0.1.0.dist-info/METADATA
jinete-0.1.0.dist-info/WHEEL
jinete-0.1.0.dist-info/top_level.txt
jinete-0.1.0.dist-info/RECORD
