Metadata-Version: 2.1
Name: jinete
Version: 0.1.0
Summary: High Performance solving suite for the Pickup and Delivery Problem and its related extensions.
Home-page: https://github.com/garciparedes/jinete
Author: Sergio García Prado
Author-email: sergio@garciparedes.me
License: UNKNOWN
Platform: UNKNOWN
Requires-Dist: cached-property (>=1.5.1)
Requires-Dist: networkx (>=2.3)
Requires-Dist: matplotlib (>=3.1.1)
Requires-Dist: seaborn (>=0.9.0)
Requires-Dist: PuLP (>=1.6.10)
Provides-Extra: all
Requires-Dist: sphinx (<3.0.0) ; extra == 'all'
Requires-Dist: sphinx-rtd-theme ; extra == 'all'
Requires-Dist: sphinxcontrib-apidoc ; extra == 'all'
Requires-Dist: sphinxcontrib-plantuml ; extra == 'all'
Requires-Dist: sphinx-autodoc-typehints ; extra == 'all'
Requires-Dist: m2r ; extra == 'all'
Requires-Dist: coverage ; extra == 'all'
Requires-Dist: codecov ; extra == 'all'
Requires-Dist: flake8 ; extra == 'all'
Requires-Dist: mypy ; extra == 'all'
Requires-Dist: coloredlogs ; extra == 'all'
Provides-Extra: docs
Requires-Dist: sphinx (<3.0.0) ; extra == 'docs'
Requires-Dist: sphinx-rtd-theme ; extra == 'docs'
Requires-Dist: sphinxcontrib-apidoc ; extra == 'docs'
Requires-Dist: sphinxcontrib-plantuml ; extra == 'docs'
Requires-Dist: sphinx-autodoc-typehints ; extra == 'docs'
Requires-Dist: m2r ; extra == 'docs'
Provides-Extra: logs
Requires-Dist: coloredlogs ; extra == 'logs'
Provides-Extra: syntax
Requires-Dist: flake8 ; extra == 'syntax'
Requires-Dist: mypy ; extra == 'syntax'
Provides-Extra: tests
Requires-Dist: coverage ; extra == 'tests'
Requires-Dist: codecov ; extra == 'tests'
